dataRT/__init__.py
dataRT/client.py
dataRT/clients.py
dataRT/http.py
dataRT/logs.py
dataRT/version.py
dataRT/websocket.py
dataRT-0.1.2.dist-info/METADATA
dataRT-0.1.2.dist-info/RECORD
dataRT-0.1.2.dist-info/WHEEL
dataRT-0.1.2.dist-info/top_level.txt
