Metadata-Version: 2.1
Name: dataRT
Version: 0.1.2
Summary: A Library for monitoring a datastream in real-time while writing data to WebSocket and InfluxDB
Home-page: https://github.com/thedeltaflyer/dataRT
Author: David Khudaverdyan
Author-email: khudaverdyan.david@gmail.com
License: MIT
Project-URL: Source, https://github.com/thedeltaflyer/dataRT/
Project-URL: Tracker, https://github.com/thedeltaflyer/dataRT/issues
Keywords: websocket influxdb realtime
Platform: UNKNOWN
Classifier: Development Status :: 3 - Alpha
Classifier: Intended Audience :: Developers
Classifier: Topic :: Software Development :: Libraries
Classifier: License :: OSI Approved :: MIT License
Classifier: Natural Language :: English
Classifier: Operating System :: OS Independent
Classifier: Programming Language :: Python :: 3
Classifier: Programming Language :: Python :: 3.6
Requires-Python: ~=3.6
Provides-Extra: test
Requires-Dist: Flask (>=0.12.2)
Requires-Dist: Flask-Sockets (>=0.2.1)
Requires-Dist: gevent (>=1.2.2)
Requires-Dist: influxdb (>=5.0.0)
Requires-Dist: requests (>=2.18.4)
Provides-Extra: test
Requires-Dist: coverage; extra == 'test'
Requires-Dist: pytest; extra == 'test'
Requires-Dist: pytest-cov; extra == 'test'
